auto_feature_engineering/__init__.py
auto_feature_engineering/feature_generator.py
auto_feature_engineering/featureprep.py
ventiotools-0.1.1.dist-info/METADATA
ventiotools-0.1.1.dist-info/WHEEL
ventiotools-0.1.1.dist-info/licenses/LICENSE.txt
ventiotools-0.1.1.dist-info/RECORD
