Metadata-Version: 2.1
Name: ventiotools
Version: 0.1.1
Summary: Tools for usage in the Vent.io ecosystem
Author-Email: Nicolas Bogun <143806426+NicolasBogun@users.noreply.github.com>
License: MIT
Classifier: Programming Language :: Python :: 3
Classifier: License :: OSI Approved :: MIT License
Classifier: Operating System :: OS Independent
Requires-Python: >=3.10
Requires-Dist: PyYAML==6.0
Requires-Dist: pyspark==3.5.0
Requires-Dist: numpy>=1.26.3
Requires-Dist: pandas>=2.1.4
Requires-Dist: pyarrow>=15.0.0
